<DOMSymbolItem xmlns="http://ns.adobe.com/xfl/2008/" xmlns:xsi="http://www.w3.org/2001/XMLSchema-instance" name="Symbol 515" lastModified="1701669489">
     <timeline>
          <DOMTimeline name="Symbol 515">
               <layers>
                    <DOMLayer name="Layer 1" color="#892deb" current="true" isSelected="true">
                         <frames>
                              <DOMFrame index="0" keyMode="9728">
                                   <elements>
                                        <DOMShape isFloating="true">
                                             <fills>
                                                  <FillStyle index="1">
                                                       <SolidColor color="#010101"/>
                                                  </FillStyle>
                                             </fills>
                                             <strokes/>
                                             <edges>
                                                  <Edge fillStyle0="1" fillStyle1="0" strokeStyle="0" edges="! 21 70| 18 60| 14 52| 14 50| 12 46| 12 44| 14 41| 16 27| 14 11| 12 2[ 9 -3 6 2[ -2 26 2 59| 10 87| 14 95| 16 98| 20 97| 22 87| 21 70"/>
                                             </edges>
                                        </DOMShape>
                                   </elements>
                              </DOMFrame>
                         </frames>
                    </DOMLayer>
               </layers>
          </DOMTimeline>
     </timeline>
</DOMSymbolItem>
