<DOMSymbolItem xmlns="http://ns.adobe.com/xfl/2008/" xmlns:xsi="http://www.w3.org/2001/XMLSchema-instance" name="Symbol 894" lastModified="1701669489" symbolType="graphic">
     <timeline>
          <DOMTimeline name="Symbol 894" currentFrame="0">
               <layers>
                    <DOMLayer name="Layer 1">
                         <frames>
                              <DOMFrame index="0" motionTweenScale="false" keyMode="8192">
                                   <elements>
                                        <DOMShape isFloating="true">
                                             <fills>
                                                  <FillStyle index="1">
                                                       <SolidColor color="#000000" alpha="0.3019608"/>
                                                  </FillStyle>
                                             </fills>
                                             <strokes/>
                                             <edges>
                                                  <Edge fillStyle0="0" fillStyle1="1" strokeStyle="0" edges="! 1307 423[ 1343 464 1356 490[ 1299 516 1273 516[ 1233 512 1195 488[ 1121 441 1121 345[ 1121 318 1130 302[ 1155 261 1241 209| 1238 235[ 1291 248 1334 328[ 1379 411 1307 423"/>
                                                  <Edge fillStyle0="0" fillStyle1="1" strokeStyle="0" edges="! 1316 1039[ 1317 1064 1336 1122[ 1353 1176 1353 1213[ 1353 1226 1345 1233| 1321 1244| 1340 1291[ 1350 1316 1350 1334[ 1350 1435 1281 1469[ 1315 1497 1311 1549[ 1311 1561 1291 1602| 1270 1645[ 1270 1661 1308 1769[ 1359 1912 1400 2112| 1441 2336| 1442 2362[ 1442 2406 1420 2426[ 1405 2440 1385 2440[ 1357 2440 1314 2424| 1298 2417| 1304 2461[ 1304 2512 1229 2552[ 1098 2622 778 2622[ 443 2622 237 2432[ 64 2272 64 2080[ 64 2067 73 2062[ 81 2058 83 2062[ 62 1943 62 1659| 66 1257| 70 1046[ 70 1005 95 980| 126 958[ 59 931 40 911[ 25 896 25 866[ 25 851 40 770| 68 635[ 85 565 79 563| 89 541| 111 484[ 200 506 205 592[ 209 648 206 820[ 283 820 364 841| 501 881[ 463 792 463 695[ 463 676 495 599[ 527 522 558 466| 581 449[ 592 714 650 797[ 696 865 827 865[ 904 865 982 830| 1085 777| 1097 775[ 1108 781 1111 792[ 1053 831 932 967[ 847 1062 776 1062[ 719 1062 678 1033| 550 946[ 541 983 533 988[ 505 1005 387 1005| 223 988[ 226 998 217 997[ 223 1010 236 994| 225 1279| 212 1765[ 219 2052 326 2193[ 390 2278 816 2344| 1252 2395| 1262 2390[ 1248 2370 1248 2347[ 1248 2328 1270 2292[ 1291 2257 1291 2243[ 1291 2133 1215 1991[ 1139 1850 1139 1811| 1176 1644| 1155 1584[ 1134 1538 1134 1523[ 1134 1468 1156 1424[ 1172 1393 1210 1349[ 1162 1296 1162 1213[ 1162 1161 1189 1100[ 1217 1039 1240 1039[ 1274 1039 1305 1058| 1316 1039"/>
                                                  <Edge fillStyle0="0" fillStyle1="1" strokeStyle="0" edges="! 1626 931[ 1626 985 1605 1019[ 1589 1046 1571 1046| 1451 1020[ 1341 993 1310 993| 1167 1008| 1047 1023| 994 1021| 993 997[ 997 949 1025 908[ 1080 827 1200 837[ 1406 855 1567 843[ 1607 844 1617 860[ 1626 875 1626 931"/>
                                                  <Edge fillStyle0="0" fillStyle1="1" strokeStyle="0" edges="! 949 2584[ 869 2588 733 2585| 516 2577| 626 2599| 743 2614| 824 2606| 949 2584"/>
                                                  <Edge fillStyle0="0" fillStyle1="1" strokeStyle="0" edges="! -394 2089[ -356 2200 -128 2279[ -9 2320 140 2351| 142 2349| 144 2362[ 144 2393 74 2420[ 16 2442 -18 2442[ -206 2442 -319 2311[ -407 2209 -407 2105[ -407 2093 -403 2091| -394 2089"/>
                                             </edges>
                                        </DOMShape>
                                   </elements>
                              </DOMFrame>
                         </frames>
                    </DOMLayer>
                    <DOMLayer name="Layer 2">
                         <frames>
                              <DOMFrame index="0" motionTweenScale="false" keyMode="8192">
                                   <elements>
                                        <DOMShape isFloating="true">
                                             <fills>
                                                  <FillStyle index="1">
                                                       <SolidColor color="#000000" alpha="1.0"/>
                                                  </FillStyle>
                                                  <FillStyle index="2">
                                                       <SolidColor color="#ffcc33" alpha="1.0"/>
                                                  </FillStyle>
                                                  <FillStyle index="3">
                                                       <SolidColor color="#ffffff" alpha="1.0"/>
                                                  </FillStyle>
                                             </fills>
                                             <strokes/>
                                             <edges>
                                                  <Edge fillStyle0="0" fillStyle1="1" strokeStyle="0" edges="! 1680 594[ 1680 633 1663 659[ 1646 686 1646 718[ 1646 738 1664 894| 1670 1067| 1658 1067| 1671 1246| 1676 1365[ 1676 1550 1614 1914[ 1546 2316 1478 2411[ 1404 2516 1241 2579[ 1039 2656 725 2656[ 372 2656 259 2578[ 218 2551 195 2504| 159 2425[ 37 2484 -44 2484[ -192 2484 -316 2375[ -462 2248 -462 2044[ -462 2008 -444 1970[ -429 1938 -408 1915[ -354 1966 -248 2015[ -149 2061 -104 2061| 33 2056| 22 1860[ 22 1818 41 1398| 45 1199| 52 999| 0 995| -10 921[ -10 818 11 647[ 35 454 58 454[ 60 342 103 230[ 190 6 410 6[ 669 6 902 61[ 1152 119 1334 232[ 1361 249 1432 339[ 1501 429 1514 463[ 1530 504 1542 506| 1565 489[ 1605 442 1651 479[ 1680 511 1680 594"/>
                                                  <Edge fillStyle0="3" fillStyle1="1" strokeStyle="0" edges="! 1140 333| 1128 357| 1254 417| 1213 498| 1438 488[ 1405 424 1331 343[ 1269 275 1226 244| 1140 333"/>
                                                  <Edge fillStyle0="0" fillStyle1="1" strokeStyle="0" edges="! 1171 206[ 1064 153 986 136[ 761 87 286 87[ 261 87 195 256| 118 460| 501 490| 558 444| 628 387| 654 365| 810 357[ 926 357 1013 411[ 1053 435 1111 495| 1156 449[ 1120 440 1092 406[ 1064 373 1064 341[ 1064 313 1098 271[ 1130 232 1171 206"/>
                                                  <Edge fillStyle0="2" fillStyle1="1" strokeStyle="0" edges="! 989 482| 921 549| 820 646[ 863 672 903 701| 824 736| 744 767[ 769 688 737 659| 712 641[ 699 630 699 616[ 699 603 705 601| 717 599| 813 642[ 823 612 889 551| 972 476| 908 455[ 835 434 781 434[ 489 434 489 626[ 489 921 627 1002[ 697 1043 775 1025[ 844 1025 937 940[ 1024 860 1080 754[ 1140 640 1125 567[ 1107 482 989 482"/>
                                                  <Edge fillStyle0="0" fillStyle1="1" strokeStyle="0" edges="! 1151 572| 1155 595| 1159 632[ 1159 707 1126 792[ 1085 897 1003 986| 1394 991| 1599 989[ 1585 934 1575 861| 1566 781| 1599 557| 1151 572"/>
                                                  <Edge fillStyle0="0" fillStyle1="1" strokeStyle="0" edges="! 91 521| 85 724| 73 929| 516 964| 472 835[ 435 718 435 673| 440 606[ 446 553 453 553| 91 521"/>
                                                  <Edge fillStyle0="0" fillStyle1="1" strokeStyle="0" edges="! 778 1082| 718 1080| 693 1070[ 601 1047 112 1004| 116 1214[ 116 1310 85 1747| 81 1880[ 81 2118 176 2315[ 309 2590 572 2590| 896 2559[ 1216 2518 1310 2466[ 1273 2449 1254 2416[ 1238 2388 1238 2355[ 1238 2321 1243 2305[ 1254 2268 1290 2255[ 1262 2236 1231 2200[ 1192 2157 1192 2130[ 1197 2082 1228 2045[ 1211 2036 1152 1928[ 1093 1819 1093 1792[ 1095 1776 1104 1756[ 1122 1716 1158 1697[ 1122 1687 1102 1663[ 1082 1639 1082 1607[ 1082 1597 1091 1572| 1100 1537| 1090 1507[ 1080 1486 1080 1476[ 1080 1432 1117 1388[ 1142 1357 1178 1333[ 1157 1318 1138 1292[ 1113 1259 1113 1234[ 1113 1207 1140 1160| 1182 1087[ 1161 1072 1128 1066| 915 1050[ 885 1051 832 1066| 778 1082"/>
                                                  <Edge fillStyle0="0" fillStyle1="1" strokeStyle="0" edges="! 402 1198[ 456 1217 460 1221| 431 1276[ 415 1308 407 1342| 406 1350[ 432 1360 470 1336[ 520 1303 533 1300[ 537 1302 534 1329[ 560 1335 583 1317| 622 1279| 630 1280[ 635 1320 601 1336| 556 1345| 522 1339| 518 1322[ 477 1363 426 1363| 390 1362[ 387 1376 387 1356| 394 1305| 400 1254| 424 1226[ 386 1214 378 1201| 361 1170| 362 1159[ 367 1145 394 1125[ 402 1126 408 1132| 389 1149| 376 1162| 401 1160| 422 1164| 432 1172| 402 1198"/>
                                                  <Edge fillStyle0="0" fillStyle1="1" strokeStyle="0" edges="! 588 1796| 634 1823[ 674 1847 674 1858| 668 1875| 658 1887| 707 1902| 687 1969[ 665 2028 665 2048| 684 2049[ 709 2049 738 2024| 779 1987| 785 1988[ 789 2003 780 2016[ 791 2018 822 2045[ 856 2045 868 2036[ 890 2036 934 1958[ 934 1945 941 1948| 953 1956[ 924 2011 897 2035[ 867 2062 828 2062[ 816 2062 798 2049[ 780 2035 767 2035| 680 2067| 661 2063[ 655 2046 655 2026[ 655 1997 661 1969[ 670 1925 690 1914[ 644 1916 633 1885[ 629 1873 630 1834[ 613 1841 598 1834[ 579 1826 582 1803| 584 1800| 588 1796"/>
                                                  <Edge fillStyle0="3" fillStyle1="1" strokeStyle="0" edges="! 1428 1187[ 1496 1218 1496 1238[ 1496 1250 1490 1250| 1476 1249| 1495 1259[ 1514 1272 1514 1284[ 1514 1294 1501 1293[ 1488 1291 1488 1301[ 1488 1313 1508 1329| 1533 1352| 1501 1375| 1478 1392[ 1489 1393 1517 1427| 1472 1457[ 1440 1473 1425 1473| 1410 1468[ 1462 1451 1500 1429| 1504 1422[ 1493 1422 1480 1411| 1465 1396[ 1477 1378 1513 1345[ 1477 1316 1479 1295| 1488 1278| 1471 1276[ 1456 1268 1467 1235[ 1447 1223 1430 1203| 1414 1179[ 1414 1169 1420 1162| 1428 1143| 1436 1139[ 1438 1144 1456 1146[ 1466 1153 1428 1187"/>
                                                  <Edge fillStyle0="3" fillStyle1="1" strokeStyle="0" edges="! 1246 1061| 1250 1071| 1253 1096[ 1253 1120 1215 1176| 1176 1239| 1288 1339| 1152 1471[ 1161 1475 1194 1501[ 1227 1528 1232 1535| 1144 1601[ 1172 1610 1196 1639[ 1221 1668 1221 1691[ 1221 1710 1191 1749[ 1160 1788 1160 1793[ 1160 1841 1243 1936| 1326 2025[ 1326 2053 1302 2077| 1254 2115[ 1310 2153 1333 2187[ 1355 2217 1355 2250[ 1355 2276 1324 2309| 1272 2361| 1399 2414[ 1509 2414 1555 2104[ 1593 1850 1593 1333| 1592 1067| 1419 1066| 1246 1061"/>
                                                  <Edge fillStyle0="3" fillStyle1="1" strokeStyle="0" edges="! 1418 1923| 1436 1938| 1473 1905| 1477 1907[ 1458 1942 1442 1949[ 1414 1949 1399 1918| 1371 1862[ 1371 1852 1381 1836[ 1407 1851 1418 1923"/>
                                                  <Edge fillStyle0="3" fillStyle1="1" strokeStyle="0" edges="! -378 2037| -383 2107[ -383 2257 -288 2319[ -186 2386 66 2386| 138 2385[ 123 2316 85 2295| 38 2287[ -111 2287 -213 2219[ -299 2163 -378 2037"/>
                                                  <Edge fillStyle0="0" fillStyle1="1" strokeStyle="0" edges="! -286 2092[ -232 2141 -128 2199[ -16 2262 31 2262| 85 2260[ 60 2177 41 2092[ 30 2118 -11 2134[ -50 2149 -97 2149[ -206 2149 -286 2092"/>
                                             </edges>
                                        </DOMShape>
                                   </elements>
                              </DOMFrame>
                         </frames>
                    </DOMLayer>
               </layers>
          </DOMTimeline>
     </timeline>
</DOMSymbolItem>
