<DOMSymbolItem xmlns="http://ns.adobe.com/xfl/2008/" xmlns:xsi="http://www.w3.org/2001/XMLSchema-instance" name="Symbol 483" lastModified="1701669489" symbolType="graphic">
     <timeline>
          <DOMTimeline name="Symbol 483" currentFrame="0">
               <layers>
                    <DOMLayer name="Layer 1">
                         <frames>
                              <DOMFrame index="0" motionTweenScale="false" keyMode="8192">
                                   <elements>
                                        <DOMShape isFloating="true">
                                             <fills>
                                                  <FillStyle index="1">
                                                       <SolidColor color="#000000" alpha="0.14901961"/>
                                                  </FillStyle>
                                             </fills>
                                             <strokes/>
                                             <edges>
                                                  <Edge fillStyle0="1" fillStyle1="0" strokeStyle="0" edges="! 837 1323[ 466 1508 361 1722[ 253 1936 304 2148[ 357 2361 391 2383| 426 2407[ 446 2448 419 2462[ 357 2483 294 2514[ 226 2547 196 2602[ 168 2656 195 2708[ 231 2780 288 2803[ 350 2826 423 2790[ 484 2760 519 2721[ 557 2680 544 2653| 534 2636| 521 2625[ 515 2620 487 2633[ 427 2701 397 2716[ 359 2735 311 2708[ 279 2687 272 2672[ 257 2639 299 2609| 400 2551[ 548 2471 494 2363| 463 2330[ 438 2313 433 2300[ 405 2245 420 2087[ 439 1881 437 1844[ 434 1805 509 1743[ 568 1690 527 1633[ 541 1588 667 1507[ 760 1447 872 1391[ 988 1334 1050 1326[ 1092 1321 1216 1322| 1184 1377| 1163 1443| 1164 1446[ 1109 1523 1032 1566[ 951 1603 904 1626[ 845 1656 794 1690[ 959 1699 1764 1830[ 1816 1803 1751 1377[ 1684 951 1747 920[ 1775 906 1925 847| 1938 848[ 1898 931 1865 1032[ 1839 1115 1842 1122[ 1931 1304 2110 1423[ 2289 1541 2318 1604[ 2482 1935 2371 2238[ 2259 2545 1913 2715[ 1678 2831 1206 2821[ 725 2813 659 2678[ 651 2662 655 2646| 660 2630[ 610 2614 606 2616[ 569 2635 575 2674| 588 2708[ 595 2724 800 2825[ 929 2888 994 2936[ 1037 2947 1094 2968| 1442 3018| 1548 3011[ 1755 2995 1903 2962| 2047 2874[ 2088 2850 2201 2768| 2314 2695[ 2404 2552 2487 2314[ 2637 1883 2479 1565[ 2456 1516 2268 1326[ 2042 1097 1944 1098| 1996 941[ 2031 828 2017 802[ 1990 746 1924 759[ 1874 770 1732 840[ 1624 892 1596 1169[ 1576 1363 1593 1497[ 1554 1456 1469 1428[ 1340 1388 1234 1459| 1224 1462| 1262 1418[ 1294 1367 1319 1304| 1300 1285| 1295 1282[ 1293 1258 1281 1240[ 1207 1140 837 1323"/>
                                                  <Edge fillStyle0="1" fillStyle1="0" strokeStyle="0" edges="! 1180 1478| 1188 1469| 1196 1472| 1180 1478"/>
                                             </edges>
                                        </DOMShape>
                                   </elements>
                              </DOMFrame>
                         </frames>
                    </DOMLayer>
                    <DOMLayer name="Layer 2">
                         <frames>
                              <DOMFrame index="0" motionTweenScale="false" keyMode="8192">
                                   <elements>
                                        <DOMShape isFloating="true">
                                             <fills>
                                                  <FillStyle index="1">
                                                       <SolidColor color="#000000" alpha="1.0"/>
                                                  </FillStyle>
                                             </fills>
                                             <strokes/>
                                             <edges>
                                                  <Edge fillStyle0="0" fillStyle1="1" strokeStyle="0" edges="! 1995 710[ 2038 710 2065 735[ 2089 757 2089 781[ 2089 810 2064 869| 1975 1064[ 2025 1120 2150 1203[ 2303 1305 2358 1351[ 2605 1557 2605 1873[ 2605 2423 2304 2734[ 2009 3040 1503 3040[ 1204 3040 924 2927[ 671 2826 568 2694| 458 2808[ 410 2850 349 2850[ 272 2850 209 2768[ 150 2692 150 2614[ 150 2559 203 2519[ 270 2469 400 2468[ 353 2400 301 2260[ 246 2113 246 2043[ 246 1907 323 1751[ 398 1599 526 1467[ 818 1168 1146 1168[ 1258 1168 1318 1242[ 1361 1296 1361 1353[ 1361 1372 1346 1389[ 1378 1390 1467 1416[ 1547 1440 1569 1451[ 1616 1336 1611 1190[ 1595 1043 1595 994[ 1595 897 1718 805[ 1845 710 1995 710"/>
                                                  <Edge fillStyle0="0" fillStyle1="1" strokeStyle="0" edges="! 1984 807[ 1896 853 1768 889[ 1708 906 1708 952| 1738 1149[ 1738 1207 1649 1504[ 1649 1515 1681 1547| 1712 1578[ 1712 1594 1694 1603| 1661 1610[ 1630 1610 1575 1549[ 1520 1488 1445 1488[ 1414 1488 1299 1517[ 1183 1545 1088 1545| 1048 1542| 1045 1541[ 1041 1539 1041 1527[ 1041 1510 1158 1446[ 1275 1383 1275 1338[ 1275 1297 1216 1284| 1154 1279| 999 1297[ 839 1323 803 1369[ 764 1417 673 1483[ 551 1570 518 1598[ 335 1756 335 1998[ 335 2194 422 2317| 481 2398[ 508 2440 508 2485[ 508 2525 465 2536| 370 2542[ 231 2542 231 2626[ 231 2660 265 2707[ 307 2764 359 2764[ 415 2764 486 2674[ 556 2583 580 2583| 641 2641[ 721 2712 823 2770[ 1153 2957 1591 2957[ 1708 2957 1848 2920[ 2021 2875 2112 2796[ 2095 2774 2095 2755[ 2198 2706 2301 2578[ 2506 2323 2506 1925[ 2506 1624 2190 1318[ 2108 1239 1973 1132[ 1874 1054 1874 1042[ 1874 1024 1881 1021| 1903 1013[ 1943 985 1984 807"/>
                                                  <Edge fillStyle0="1" fillStyle1="0" strokeStyle="0" edges="! 1968 850[ 1966 828 1935 842[ 1874 948 1871 965[ 1899 992 1931 936[ 1952 901 1968 850"/>
                                                  <Edge fillStyle0="1" fillStyle1="0" strokeStyle="0" edges="! 1214 1330| 1196 1318| 1180 1321[ 1150 1337 1124 1363| 1078 1409[ 1075 1412 1083 1429[ 1096 1456 1132 1425| 1214 1330"/>
                                             </edges>
                                        </DOMShape>
                                   </elements>
                              </DOMFrame>
                         </frames>
                    </DOMLayer>
               </layers>
          </DOMTimeline>
     </timeline>
</DOMSymbolItem>
