<DOMSymbolItem xmlns="http://ns.adobe.com/xfl/2008/" xmlns:xsi="http://www.w3.org/2001/XMLSchema-instance" name="Symbol 90" lastModified="1701669489" linkageClassName="fl.controls.TextInput" linkageExportForAS="true">
     <timeline>
          <DOMTimeline name="Symbol 90">
               <layers>
                    <DOMLayer name="Layer 1" color="#cfaeac">
                         <frames>
                              <DOMFrame index="0" keyMode="9728">
                                   <elements/>
                              </DOMFrame>
                              <DOMFrame index="1" keyMode="9728">
                                   <elements>
                                        <DOMSymbolInstance libraryItemName="Symbol 77" centerPoint3DX="126.4" centerPoint3DY="124.35">
                                             <matrix>
                                                  <Matrix tx="85.4" ty="113.35"/>
                                             </matrix>
                                             <transformationPoint>
                                                  <Point/>
                                             </transformationPoint>
                                        </DOMSymbolInstance>
                                   </elements>
                              </DOMFrame>
                         </frames>
                    </DOMLayer>
                    <DOMLayer name="Layer 2" color="#b0dffb">
                         <frames>
                              <DOMFrame index="0" keyMode="9728">
                                   <elements/>
                              </DOMFrame>
                              <DOMFrame index="1" keyMode="9728">
                                   <elements>
                                        <DOMSymbolInstance libraryItemName="Symbol 89" centerPoint3DX="91.45" centerPoint3DY="29.2">
                                             <matrix>
                                                  <Matrix tx="15.45" ty="18.2"/>
                                             </matrix>
                                             <transformationPoint>
                                                  <Point/>
                                             </transformationPoint>
                                        </DOMSymbolInstance>
                                   </elements>
                              </DOMFrame>
                         </frames>
                    </DOMLayer>
                    <DOMLayer name="Layer 3" color="#8de1ed">
                         <frames>
                              <DOMFrame index="0" keyMode="9728">
                                   <elements/>
                              </DOMFrame>
                              <DOMFrame index="1" keyMode="9728">
                                   <elements>
                                        <DOMSymbolInstance libraryItemName="Symbol 87" centerPoint3DX="91.45" centerPoint3DY="76.65">
                                             <matrix>
                                                  <Matrix tx="15.45" ty="65.65"/>
                                             </matrix>
                                             <transformationPoint>
                                                  <Point/>
                                             </transformationPoint>
                                        </DOMSymbolInstance>
                                   </elements>
                              </DOMFrame>
                         </frames>
                    </DOMLayer>
                    <DOMLayer name="Layer 4" color="#489be4" current="true" isSelected="true">
                         <frames>
                              <DOMFrame index="0" keyMode="9728">
                                   <elements>
                                        <DOMSymbolInstance libraryItemName="Symbol 56" centerPoint3DX="40.0" centerPoint3DY="11.0">
                                             <matrix>
                                                  <Matrix tx="0.0" ty="0.0" a="1.25" d="1.0"/>
                                             </matrix>
                                             <transformationPoint>
                                                  <Point/>
                                             </transformationPoint>
                                        </DOMSymbolInstance>
                                   </elements>
                              </DOMFrame>
                              <DOMFrame index="1" keyMode="9728">
                                   <elements>
                                        <DOMSymbolInstance libraryItemName="Symbol 57" centerPoint3DX="10.0" centerPoint3DY="10.0">
                                             <matrix>
                                                  <Matrix tx="10.0" ty="10.0" a="1.0" d="1.00311279296875"/>
                                             </matrix>
                                             <transformationPoint>
                                                  <Point/>
                                             </transformationPoint>
                                        </DOMSymbolInstance>
                                   </elements>
                              </DOMFrame>
                         </frames>
                    </DOMLayer>
               </layers>
          </DOMTimeline>
     </timeline>
</DOMSymbolItem>
